{"textures":{"0":"modelengine:entity/squirrel"},"elements":[{"name":"cube","from":[8.6,7.85,6.95],"to":[8.9,8.15,7.85],"rotation":{"angle":0.0,"axis":"x","origin":[8.0,7.85,6.95]},"faces":{"down":{"uv":[8.5,7.5,8.0,9.0],"rotation":0,"texture":"#0","tintindex":0},"east":{"uv":[2.0,6.5,3.5,7.0],"rotation":0,"texture":"#0","tintindex":0},"north":{"uv":[9.5,1.0,10.0,1.5],"rotation":0,"texture":"#0","tintindex":0},"south":{"uv":[9.5,6.5,10.0,7.0],"rotation":0,"texture":"#0","tintindex":0},"up":{"uv":[8.0,9.0,7.5,7.5],"rotation":0,"texture":"#0","tintindex":0},"west":{"uv":[7.5,1.5,9.0,2.0],"rotation":0,"texture":"#0","tintindex":0}}},{"name":"cube","from":[7.1,7.85,6.95],"to":[7.4,8.15,7.85],"rotation":{"angle":0.0,"axis":"x","origin":[8.0,7.85,6.95]},"faces":{"down":{"uv":[4.5,8.5,4.0,10.0],"rotation":0,"texture":"#0","tintindex":0},"east":{"uv":[2.0,8.5,3.5,9.0],"rotation":0,"texture":"#0","tintindex":0},"north":{"uv":[8.0,9.5,8.5,10.0],"rotation":0,"texture":"#0","tintindex":0},"south":{"uv":[9.5,8.0,10.0,8.5],"rotation":0,"texture":"#0","tintindex":0},"up":{"uv":[4.0,10.0,3.5,8.5],"rotation":0,"texture":"#0","tintindex":0},"west":{"uv":[8.5,2.0,10.0,2.5],"rotation":0,"texture":"#0","tintindex":0}}}],"display":{"head":{"translation":[0.0,-6.4,0.0],"rotation":[0.0,0.0,0.0],"scale":[3.8095,3.8095,3.8095]}}}