{"textures":{"0":"modelengine:entity/frog"},"elements":[{"name":"right_foot","from":[10.706,4.802,6.4976],"to":[12.182,5.2939997,9.4496],"rotation":{"angle":0.0,"axis":"x","origin":[9.476,3.3259997,5.6096]},"faces":{"down":{"uv":[13.25,2.25,12.5,3.75],"rotation":0,"texture":"#0","tintindex":0},"east":{"uv":[11.75,3.75,13.25,4.0],"rotation":0,"texture":"#0","tintindex":0},"north":{"uv":[13.25,3.75,14.0,4.0],"rotation":0,"texture":"#0","tintindex":0},"south":{"uv":[11.0,3.75,11.75,4.0],"rotation":0,"texture":"#0","tintindex":0},"up":{"uv":[14.0,3.75,13.25,2.25],"rotation":0,"texture":"#0","tintindex":0},"west":{"uv":[14.0,3.75,15.5,4.0],"rotation":0,"texture":"#0","tintindex":0}}}],"display":{"head":{"translation":[0.0,-6.4,0.0],"rotation":[0.0,0.0,0.0],"scale":[3.8095,3.8095,3.8095]}}}