{"textures":{"0":"modelengine:entity/fallen"},"elements":[{"name":"cube","from":[6.974,3.842,7.19],"to":[8.486,8.162001,8.702],"rotation":{"angle":0.0,"axis":"x","origin":[7.73,6.434,7.946]},"faces":{"down":{"uv":[4.0,10.5,3.25,11.25],"rotation":0,"texture":"#0","tintindex":0},"east":{"uv":[5.75,6.75,6.5,8.5],"rotation":0,"texture":"#0","tintindex":0},"north":{"uv":[5.0,6.75,5.75,8.5],"rotation":0,"texture":"#0","tintindex":0},"south":{"uv":[2.0,7.0,2.75,8.75],"rotation":0,"texture":"#0","tintindex":0},"up":{"uv":[4.75,3.75,4.0,3.0],"rotation":0,"texture":"#0","tintindex":0},"west":{"uv":[2.75,7.0,3.5,8.75],"rotation":0,"texture":"#0","tintindex":0}}},{"name":"cube","from":[7.19,3.3019998,7.1468],"to":[8.27,4.382,8.745199],"rotation":{"angle":0.0,"axis":"x","origin":[7.73,5.7860003,7.946]},"faces":{"down":{"uv":[2.5,6.25,2.0,7.0],"rotation":0,"texture":"#0","tintindex":0},"east":{"uv":[7.5,7.0,8.25,7.5],"rotation":0,"texture":"#0","tintindex":0},"north":{"uv":[9.0,4.0,9.5,4.5],"rotation":0,"texture":"#0","tintindex":0},"south":{"uv":[6.0,11.5,6.5,12.0],"rotation":0,"texture":"#0","tintindex":0},"up":{"uv":[3.0,5.75,2.5,5.0],"rotation":0,"texture":"#0","tintindex":0},"west":{"uv":[2.5,11.0,3.25,11.5],"rotation":0,"texture":"#0","tintindex":0}}},{"name":"cube","from":[6.758,6.434,6.974],"to":[8.702,8.162001,8.917999],"rotation":{"angle":0.0,"axis":"x","origin":[7.73,6.434,7.946]},"faces":{"down":{"uv":[4.75,10.75,4.0,11.5],"rotation":0,"texture":"#0","tintindex":0},"east":{"uv":[10.5,4.75,11.25,5.5],"rotation":0,"texture":"#0","tintindex":0},"north":{"uv":[10.5,4.0,11.25,4.75],"rotation":0,"texture":"#0","tintindex":0},"south":{"uv":[10.5,5.5,11.25,6.25],"rotation":0,"texture":"#0","tintindex":0},"up":{"uv":[11.25,10.25,10.5,9.5],"rotation":0,"texture":"#0","tintindex":0},"west":{"uv":[10.5,6.25,11.25,7.0],"rotation":0,"texture":"#0","tintindex":0}}}],"display":{"head":{"translation":[0.0,-6.4,0.0],"rotation":[0.0,0.0,0.0],"scale":[3.8095,3.8095,3.8095]}}}